DLNAPlayOn/PlayOn.py
DLNAPlayOn/README.md
DLNAPlayOn/__init__.py
DLNAPlayOn/ffmpeg.bat
DLNAPlayOn/youtube-dl.bat
DLNAPlayOn-1.8.3.dist-info/LICENSE
DLNAPlayOn-1.8.3.dist-info/METADATA
DLNAPlayOn-1.8.3.dist-info/WHEEL
DLNAPlayOn-1.8.3.dist-info/top_level.txt
DLNAPlayOn-1.8.3.dist-info/RECORD
